{
  "annotations": {
    "list": [
      {
        "builtIn": 1,
        "datasource": "-- Grafana --",
        "enable": true,
        "hide": true,
        "iconColor": "rgba(0, 211, 255, 1)",
        "name": "Annotations & Alerts",
        "type": "dashboard"
      }
    ]
  },
  "editable": true,
  "gnetId": null,
  "graphTooltip": 0,
  "id": 5,
  "links": [],
  "panels": [
    {
      "collapsed": false,
      "datasource": null,
      "gridPos": {
        "h": 1,
        "w": 24,
        "x": 0,
        "y": 0
      },
      "id": 2,
      "panels": [],
      "title": "Last Month's Throughput",
      "type": "row"
    },
    {
      "datasource": null,
      "description": "Last Month's Deployment Frequency per Application, (Namespace), Average per Day",
      "fieldConfig": {
        "defaults": {
          "custom": {},
          "mappings": [],
          "thresholds": {
            "mode": "absolute",
            "steps": [
              {
                "color": "light-red",
                "value": null
              },
              {
                "color": "light-yellow",
                "value": 5
              },
              {
                "color": "light-green",
                "value": 8
              }
            ]
          }
        },
        "overrides": []
      },
      "gridPos": {
        "h": 5,
        "w": 24,
        "x": 0,
        "y": 1
      },
      "id": 4,
      "options": {
        "reduceOptions": {
          "calcs": [
            "mean"
          ],
          "fields": "",
          "values": false
        },
        "showThresholdLabels": false,
        "showThresholdMarkers": true
      },
      "pluginVersion": "7.3.5",
      "targets": [
        {
          "expr": "increase(deployed_count[30d])/30",
          "interval": "",
          "legendFormat": "{{app}} ({{namespace}})",
          "refId": "A"
        }
      ],
      "timeFrom": null,
      "timeShift": null,
      "title": "Last Month's Throughput (per Application (Namespace), Average per Day)",
      "type": "gauge"
    },
    {
      "datasource": null,
      "gridPos": {
        "h": 1,
        "w": 24,
        "x": 0,
        "y": 6
      },
      "id": 6,
      "title": "Last Year's Throughput",
      "type": "row"
    },
    {
      "datasource": null,
      "description": "Last Year's Deployment Frequency per Application, (Namespace), Average per Day)",
      "fieldConfig": {
        "defaults": {
          "custom": {},
          "mappings": [],
          "thresholds": {
            "mode": "absolute",
            "steps": [
              {
                "color": "light-red",
                "value": null
              },
              {
                "color": "light-yellow",
                "value": 5
              },
              {
                "color": "light-green",
                "value": 8
              }
            ]
          }
        },
        "overrides": []
      },
      "gridPos": {
        "h": 5,
        "w": 24,
        "x": 0,
        "y": 7
      },
      "id": 8,
      "options": {
        "reduceOptions": {
          "calcs": [
            "mean"
          ],
          "fields": "",
          "values": false
        },
        "showThresholdLabels": false,
        "showThresholdMarkers": true
      },
      "pluginVersion": "7.3.5",
      "targets": [
        {
          "expr": "increase(deployed_count[365d])/365",
          "interval": "",
          "legendFormat": "{{app}} ({{namespace}})",
          "refId": "A"
        }
      ],
      "timeFrom": null,
      "timeShift": null,
      "title": "Last Year's Throughput (per Application (Namespace), Average per Day)",
      "type": "gauge"
    }
  ],
  "refresh": "1m",
  "schemaVersion": 26,
  "style": "dark",
  "tags": [],
  "templating": {
    "list": []
  },
  "time": {
    "from": "now-6h",
    "to": "now"
  },
  "timepicker": {},
  "timezone": "",
  "title": "Long-term Throughput Gauges",
  "uid": "Klm1fLyGz",
  "version": 7
}